fundb/__init__.py
fundb/json/__init__.py
fundb/json/jsonextendsclass.py
fundb/sqlalchemy/__init__.py
fundb/sqlalchemy/base.py
fundb/sqlalchemy/engine.py
fundb/sqlalchemy/table.py
funddb-1.3.14.dist-info/METADATA
funddb-1.3.14.dist-info/WHEEL
funddb-1.3.14.dist-info/top_level.txt
funddb-1.3.14.dist-info/RECORD
