Metadata-Version: 2.1
Name: funddb
Version: 1.3.14
Summary: funddb
Author-email: niuliangtao <farfarfun@qq.com>
Requires-Python: >=3.7
Requires-Dist: funutil>=1.0.19
Requires-Dist: sqlalchemy>=2.0.36
